rstmdb/__init__.py
rstmdb/client.py
rstmdb/connection.py
rstmdb/errors.py
rstmdb/models.py
rstmdb/protocol.py
rstmdb/py.typed
rstmdb/tls.py
rstmdb-0.1.0.dist-info/METADATA
rstmdb-0.1.0.dist-info/WHEEL
rstmdb-0.1.0.dist-info/licenses/LICENSE
rstmdb-0.1.0.dist-info/RECORD
