Metadata-Version: 2.4
Name: rstmdb
Version: 0.1.0
Summary: Python client library for rstmdb server using RCP protocol
Project-URL: Homepage, https://github.com/rstmdb/rstmdb-py
Project-URL: Documentation, https://github.com/rstmdb/rstmdb-py#readme
Project-URL: Repository, https://github.com/rstmdb/rstmdb-py
Author: rstmdb contributors
License-Expression: MIT
License-File: LICENSE
Classifier: Development Status :: 3 - Alpha
Classifier: Intended Audience :: Developers
Classifier: License :: OSI Approved :: MIT License
Classifier: Programming Language :: Python :: 3
Classifier: Programming Language :: Python :: 3.10
Classifier: Programming Language :: Python :: 3.11
Classifier: Programming Language :: Python :: 3.12
Classifier: Typing :: Typed
Requires-Python: >=3.10
Requires-Dist: pydantic>=2.0
Provides-Extra: dev
Requires-Dist: mypy>=1.0; extra == 'dev'
Requires-Dist: pytest-asyncio>=0.21; extra == 'dev'
Requires-Dist: pytest>=7.0; extra == 'dev'
Requires-Dist: ruff>=0.1; extra == 'dev'
Requires-Dist: tox>=4.0; extra == 'dev'
